fuxion/.ipynb_checkpoints/Untitled-checkpoint.ipynb
fuxion/.langchain.db
fuxion/__init__.py
fuxion/datasets/emotions_dataset.json
fuxion/datasets/emotions_dataset2.json
fuxion/datasets/emotions_dataset3.json
fuxion/datasets/irp_dataset_test_a.json
fuxion/datasets/irp_dataset_test_b.json
fuxion/datasets/irp_dataset_test_x.json
fuxion/datasets/irp_dataset_test_y.json
fuxion/datasets/irp_dataset_test_z.json
fuxion/datasets/name_pipeline.json
fuxion/datasets/name_pipeline_100.json
fuxion/datasets/puzzle_dataset.json
fuxion/datasets/puzzle_dataset_10.json
fuxion/datasets/puzzle_dataset_2.json
fuxion/datasets/puzzle_dataset_3.json
fuxion/datasets/puzzle_dataset_4.json
fuxion/datasets/puzzle_dataset_5.json
fuxion/datasets/puzzle_dataset_6.json
fuxion/datasets/puzzle_dataset_7.json
fuxion/datasets/puzzle_dataset_8.json
fuxion/datasets/puzzle_dataset_9.json
fuxion/dynamic_models.py
fuxion/examples/.langchain.db
fuxion/examples/name_generator/.langchain.db
fuxion/examples/name_generator/few_shot.json
fuxion/examples/name_generator/generator.template
fuxion/examples/name_generator/name_pipeline.py
fuxion/few_shot.py
fuxion/finetuning/.langchain.db
fuxion/finetuning/dataset.py
fuxion/finetuning/emotion/emotion.json
fuxion/finetuning/emotion/emotion_pipeline.py
fuxion/finetuning/emotion/generator.template
fuxion/finetuning/emotion/normalizer.template
fuxion/finetuning/llm_cache.db
fuxion/finetuning/predict.py
fuxion/finetuning/puzzle/generator.template
fuxion/finetuning/puzzle/normalizer.template
fuxion/finetuning/puzzle/puzzle.json
fuxion/finetuning/puzzle/puzzle_pipeline.py
fuxion/finetuning/train.py
fuxion/generators.py
fuxion/irp/generator.template
fuxion/irp/irp.json
fuxion/irp/irp_pipeline.py
fuxion/irp/normalizer.template
fuxion/llm_cache.db
fuxion/models.py
fuxion/pipelines.py
fuxion/settings.py
fuxion-0.0.4.2.dist-info/LICENSE
fuxion-0.0.4.2.dist-info/METADATA
fuxion-0.0.4.2.dist-info/WHEEL
fuxion-0.0.4.2.dist-info/RECORD
