Metadata-Version: 2.1
Name: fuxion
Version: 0.0.4.2
Summary: Synthetic dataset generation and normalization functions powered by LLMs
License: MIT
Author: Oluwatobi Adefami
Author-email: tobiadefami@gmail.com
Requires-Python: >=3.10,<4.0
Classifier: License :: OSI Approved :: MIT License
Classifier: Programming Language :: Python :: 3
Classifier: Programming Language :: Python :: 3.10
Classifier: Programming Language :: Python :: 3.11
Requires-Dist: Jinja2 (>=3.1.2,<4.0.0)
Requires-Dist: langchain (>=0.3.0,<0.4.0)
Requires-Dist: langchain-community (>=0.3.0,<0.4.0)
Requires-Dist: langchain-openai (>=0.2.0,<0.3.0)
Requires-Dist: openai (>=1.46.1,<2.0.0)
Requires-Dist: typer (>=0.12.5,<0.13.0)
